ExtPep_identifier/__init__.py
ExtPep_identifier/aho_corasick.py
ExtPep_identifier/api_final.py
ExtPep_identifier/calculations_and_plot.py
ExtPep_identifier/sequence_process.py
extPep_identifier_blackjack-0.0.9.dist-info/LICENSE
extPep_identifier_blackjack-0.0.9.dist-info/METADATA
extPep_identifier_blackjack-0.0.9.dist-info/WHEEL
extPep_identifier_blackjack-0.0.9.dist-info/top_level.txt
extPep_identifier_blackjack-0.0.9.dist-info/RECORD
