Metadata-Version: 2.1
Name: extPep-identifier-blackjack
Version: 0.0.9
Summary: Extended peptides identification given mass-spec search result and custom proteomic database
Home-page: http://git.pepchem.org/gaolab/api_ribo_ext 
Author: Xinhao Shao
Author-email: 
License: UNKNOWN
Platform: UNKNOWN
Classifier: Programming Language :: Python :: 3
Classifier: License :: OSI Approved :: MIT License
Classifier: Operating System :: OS Independent
Requires-Python: >=3.6
